kfa/__init__.py
kfa/forced_alignment.py
kfa/g2p.fst
kfa/lexicon.pkl
kfa/number_verbalize.py
kfa/text_normalize.py
kfa/utils.py
kfa-0.2.0.data/scripts/kfa
kfa-0.2.0.dist-info/METADATA
kfa-0.2.0.dist-info/WHEEL
kfa-0.2.0.dist-info/top_level.txt
kfa-0.2.0.dist-info/RECORD
