Metadata-Version: 2.1
Name: kfa
Version: 0.2.0
Summary: Khmer Forced Aligner powered by Wav2Vec2CTC and Phonetisaurus
Home-page: https://github.com/seanghay/kfa
Author: Seanghay Yath
Author-email: seanghay.dev@gmail.com
License: Apache License 2.0
Classifier: Programming Language :: Python :: 3
Classifier: Operating System :: OS Independent
Classifier: Intended Audience :: Developers
Classifier: Natural Language :: English
Requires-Python: >3.5
Requires-Dist: chardet >=5.2.0
Requires-Dist: onnxruntime >=1.16.0
Requires-Dist: sosap ==0.0.1
Requires-Dist: numpy >=1.24.4
Requires-Dist: khmercut ==0.0.2
Requires-Dist: librosa >=0.10.1
Requires-Dist: requests >=2.31.0
Requires-Dist: appdirs >=1.4.4
